bidirectional_cross_attention/__init__.py
bidirectional_cross_attention/bidirectional_cross_attention.py
bidirectional_cross_attention-0.1.0.dist-info/licenses/LICENSE
bidirectional_cross_attention-0.1.0.dist-info/METADATA
bidirectional_cross_attention-0.1.0.dist-info/WHEEL
bidirectional_cross_attention-0.1.0.dist-info/top_level.txt
bidirectional_cross_attention-0.1.0.dist-info/RECORD
